MANIFEST.in
README.rst
setup.cfg
setup.py
doc/Makefile
doc/array.rst
doc/codegen.rst
doc/conf.py
doc/dag.rst
doc/design.rst
doc/index.rst
doc/internal.rst
doc/make.bat
doc/misc.rst
examples/advection.py
examples/demo.py
examples/dg_tools.py
examples/einsum.py
examples/reduction.py
examples/visualization.py
pytato/__init__.py
pytato/array.py
pytato/codegen.py
pytato/diagnostic.py
pytato/loopy.py
pytato/scalar_expr.py
pytato/transform.py
pytato/utils.py
pytato/version.py
pytato/visualization.py
pytato.egg-info/PKG-INFO
pytato.egg-info/SOURCES.txt
pytato.egg-info/dependency_links.txt
pytato.egg-info/requires.txt
pytato.egg-info/top_level.txt
pytato/target/__init__.py
pytato/target/loopy/__init__.py
pytato/target/loopy/codegen.py
test/test_codegen.py
test/test_pytato.py
test/testlib.py